rpi3.torch-0.1.0.dist-info/DESCRIPTION.rst
rpi3.torch-0.1.0.dist-info/LICENSE.txt
rpi3.torch-0.1.0.dist-info/METADATA
rpi3.torch-0.1.0.dist-info/RECORD
rpi3.torch-0.1.0.dist-info/WHEEL
rpi3.torch-0.1.0.dist-info/metadata.json
rpi3.torch-0.1.0.dist-info/top_level.txt
torch/_C.cpython-35m-arm-linux-gnueabihf.so
torch/__init__.py
torch/_dl.cpython-35m-arm-linux-gnueabihf.so
torch/_six.py
torch/_storage_docs.py
torch/_tensor_docs.py
torch/_tensor_str.py
torch/_torch_docs.py
torch/_utils.py
torch/functional.py
torch/random.py
torch/serialization.py
torch/storage.py
torch/tensor.py
torch/version.py
torch/_thnn/__init__.py
torch/_thnn/utils.py
torch/autograd/__init__.py
torch/autograd/function.py
torch/autograd/grad_mode.py
torch/autograd/gradcheck.py
torch/autograd/profiler.py
torch/autograd/variable.py
torch/autograd/_functions/__init__.py
torch/autograd/_functions/tensor.py
torch/autograd/_functions/utils.py
torch/backends/__init__.py
torch/backends/cudnn/__init__.py
torch/backends/cudnn/rnn.py
torch/backends/mkl/__init__.py
torch/contrib/__init__.py
torch/contrib/_graph_vis.py
torch/cuda/__init__.py
torch/cuda/comm.py
torch/cuda/error.py
torch/cuda/nccl.py
torch/cuda/nvtx.py
torch/cuda/profiler.py
torch/cuda/random.py
torch/cuda/sparse.py
torch/cuda/streams.py
torch/distributed/__init__.py
torch/distributed/launch.py
torch/distributed/remote_types.py
torch/distributions/__init__.py
torch/distributions/bernoulli.py
torch/distributions/beta.py
torch/distributions/binomial.py
torch/distributions/categorical.py
torch/distributions/cauchy.py
torch/distributions/chi2.py
torch/distributions/constraint_registry.py
torch/distributions/constraints.py
torch/distributions/dirichlet.py
torch/distributions/distribution.py
torch/distributions/exp_family.py
torch/distributions/exponential.py
torch/distributions/fishersnedecor.py
torch/distributions/gamma.py
torch/distributions/geometric.py
torch/distributions/gumbel.py
torch/distributions/independent.py
torch/distributions/kl.py
torch/distributions/laplace.py
torch/distributions/log_normal.py
torch/distributions/logistic_normal.py
torch/distributions/multinomial.py
torch/distributions/multivariate_normal.py
