Metadata-Version: 2.0
Name: rpi3.torch
Version: 0.1.0
Summary: PyTorch in Raspberry Pi3 B, py35, armv7l
Home-page: UNKNOWN
Author: Kit
Author-email: UNKNOWN
License: UNKNOWN
Platform: UNKNOWN
